gitingest_mcp/__init__.py
gitingest_mcp/ingest.py
gitingest_mcp/server.py
mseep_gitingest_mcp-0.1.3.dist-info/METADATA
mseep_gitingest_mcp-0.1.3.dist-info/WHEEL
mseep_gitingest_mcp-0.1.3.dist-info/entry_points.txt
mseep_gitingest_mcp-0.1.3.dist-info/licenses/LICENSE
mseep_gitingest_mcp-0.1.3.dist-info/RECORD
